pyadtpulse/.vscode/settings.json
pyadtpulse/__init__.py
pyadtpulse/alarm_panel.py
pyadtpulse/const.py
pyadtpulse/exceptions.py
pyadtpulse/fingerprint.json
pyadtpulse/gateway.py
pyadtpulse/pulse_authentication_properties.py
pyadtpulse/pulse_backoff.py
pyadtpulse/pulse_connection.py
pyadtpulse/pulse_connection_properties.py
pyadtpulse/pulse_connection_status.py
pyadtpulse/pulse_query_manager.py
pyadtpulse/pyadtpulse_async.py
pyadtpulse/pyadtpulse_properties.py
pyadtpulse/site.py
pyadtpulse/site_properties.py
pyadtpulse/util.py
pyadtpulse/zones.py
pyadtpulse-1.2.12.dist-info/WHEEL
pyadtpulse-1.2.12.dist-info/METADATA
pyadtpulse-1.2.12.dist-info/RECORD
