Metadata-Version: 2.4
Name: pyadtpulse
Version: 1.2.12
Summary: Python interface for ADT Pulse security systems
Author: Ryan Snodgrass
License-Expression: Apache-2.0
Classifier: Development Status :: 5 - Production/Stable
Classifier: License :: OSI Approved :: Apache Software License
Classifier: Intended Audience :: Developers
Classifier: Operating System :: OS Independent
Classifier: Programming Language :: Python :: 3
Classifier: Programming Language :: Python :: 3.10
Classifier: Programming Language :: Python :: 3.11
Classifier: Programming Language :: Python :: 3.12
Classifier: Programming Language :: Python :: 3.13
Requires-Dist: aiohttp>=3.12.14
Requires-Dist: aiohttp-fast-zlib[zlib-ng]>=0.3.0
Requires-Dist: lxml>=6.0.0
Requires-Dist: uvloop>=0.21.0
Maintainer: Elliot Worth
Maintainer-email: Elliot Worth <elliotworth@protonmail.com>
Requires-Python: >=3.12, <3.14
